{
  "version": "1.0.3",
  "version_code": 10003,
  "apk_url": "https://quran-foundation-prime.lovable.app/downloads/noor-quran-1.0.3.apk",
  "downloadUrl": "https://quran-foundation-prime.lovable.app/downloads/noor-quran-1.0.3.apk",
  "message": "تحديث جديد لتطبيق نور القرآن الكريم — أيقونة «الشكل» لتغيير مظهر التطبيق، وإصلاحات في قالب الفجر والسبحة وصفحة قراءة القرآن.",
  "changelog": [
    "🎨 أيقونة «الشكل» أسفل الشاشة لتغيير شكل التطبيق: اللون، ونمط العرض، وقالب الفجر — مع معاينة حية وحفظ تلقائي",
    "🔗 تفعيل زر المشاركة في قالب الفجر ليفتح قائمة المشاركة وتختار التطبيق",
    "🌙 إصلاح الأزرار والنصوص المختفية في الوضع الليلي لقالب الفجر",
    "📖 أزرار التصفية (الكل / مكية / مدنية) في صفحة القرآن بخلفية بيضاء ونص أسود",
    "📿 تصحيح ذكر «سبحان الله العظيم» في السبحة بإزالة «وبحمده»",
    "⚡ تحسينات عامة في الأداء والاستقرار"
  ],
  "mandatory": false,
  "force_update_below": "0.9.0",
  "min_android_version": 21,
  "released_at": "2026-06-24"
}
